routedsl/__init__.py
routedsl/bricks.py
routedsl/dsl.py
routedsl/ops.py
tests/__init__.py
tests/test_dsl.py
routedsl-0.0.1.dist-info/LICENSE
routedsl-0.0.1.dist-info/METADATA
routedsl-0.0.1.dist-info/WHEEL
routedsl-0.0.1.dist-info/top_level.txt
routedsl-0.0.1.dist-info/RECORD
