Metadata-Version: 2.1
Name: routedsl
Version: 0.0.1
Summary: Route DSL
Home-page: https://maximavanov.com/
Author: Maxim Avanov
Author-email: maxim.avanov@gmail.com
License: UNKNOWN
Keywords: web
Platform: UNKNOWN
Classifier: Development Status :: 1 - Planning
Classifier: Intended Audience :: Developers
Classifier: License :: OSI Approved
Classifier: License :: OSI Approved :: MIT License
Classifier: Programming Language :: Python
Classifier: Programming Language :: Python :: 3
Classifier: Operating System :: POSIX
Classifier: Topic :: Internet :: WWW/HTTP
Requires-Dist: typeit (>=0.24.0)
Requires-Dist: routes (==2.4.1)
Requires-Dist: infix (==1.2)
